{
  "data": [
    {
      "id": 32,
      "name": "Machine Learning",
      "background": "#FFFFFF",
      "client": {
        "id": 1,
        "name": "Code Engine Studio"
      },
      "tracked_time": 0,
      "member": [
        {
          "id": 1,
          "first_name": null,
          "last_name": null,
          "email": "levanlinhcube@gmail.com",
          "image": null
        },
        {
          "id": 2,
          "first_name": null,
          "last_name": null,
          "email": "lynleva.cube.it141@gmail.com",
          "image": null
        },
        {
          "id": 3,
          "first_name": null,
          "last_name": null,
          "email": "cubesit@gmail.com",
          "image": null
        }
      ]
    },
    {
      "id": 31,
      "name": "Zilly",
      "background": "#FFFFFF",
      "client": {
        "id": 1,
        "name": "Code Engine Studio"
      },
      "tracked_time": 0,
      "member": [
        {
          "id": 1,
          "first_name": null,
          "last_name": null,
          "email": "levanlinhcube@gmail.com",
          "image": null
        },
        {
          "id": 2,
          "first_name": null,
          "last_name": null,
          "email": "lynleva.cube.it141@gmail.com",
          "image": null
        },
        {
          "id": 3,
          "first_name": null,
          "last_name": null,
          "email": "cubesit@gmail.com",
          "image": null
        }
      ]
    },
    {
      "id": 30,
      "name": "Time Cloud",
      "background": "#FFFFFF",
      "client": {
        "id": 1,
        "name": "Code Engine Studio"
      },
      "tracked_time": 86400,
      "member": [
        {
          "id": 1,
          "first_name": null,
          "last_name": null,
          "email": "levanlinhcube@gmail.com",
          "image": null
        },
        {
          "id": 2,
          "first_name": null,
          "last_name": null,
          "email": "lynleva.cube.it141@gmail.com",
          "image": null
        },
        {
          "id": 3,
          "first_name": null,
          "last_name": null,
          "email": "cubesit@gmail.com",
          "image": null
        }
      ]
    }
  ]
}